Workbook
Name Aporte: Plan1!$C$17
Name Património: Plan1!$C$20
Name Sugst_Inve: Plan1!$H$20
Name Sugst_Inves: Plan1!$C$14
Name Taxa_Cart: Plan1!$C$13
Name Taxa_Renda_Mensal: Plan1!$C$19
Name Tempo_em_ano: Plan1!$C$18

Sheet Plan1
B11: CONFIGURAÇÕES
B12: Salário | C12: 3000
B13: Rendimento carteira | C13: 0.006
B14: Sugestão de investimento (30%) | C14: =C12*30% -> 900
B16: INVESTIMENTO MENSAL
B17: Quanto investir por mês? | C17: 350
B18: Por quantos anos? | C18: 5
B19: Taxa de Rendimento mensal? | C19: 0.01079
B20: Patrimônio acumulado? | C20: =FV(Taxa_Renda_Mensal,Tempo_em_ano*12,Aporte*-1) -> 29321.92
B21: Dividendos mensais? | C21: =C20*Taxa_Cart -> 175.93152
B23: CENÁRIOS | C23: DIVIDENDOS
A24: 2 | B24: Quanto em 2 anos | C24: =FV(Taxa_Renda_Mensal,$A24*12,Aporte*-1) -> 9529.6696 | D24: =C24*Taxa_Cart -> 57.178017
A25: 5 | B25: Quanto em 5 anos | C25: =FV(Taxa_Renda_Mensal,$A25*12,Aporte*-1) -> 29321.92 | D25: =C25*Taxa_Cart -> 175.93152
A26: 10 | B26: Quanto em 10 anos | C26: =FV(Taxa_Renda_Mensal,$A26*12,Aporte*-1) -> 85149.474 | D26: =C26*Taxa_Cart -> 510.89685
A27: 20 | B27: Quanto em 20 anos | C27: =FV(Taxa_Renda_Mensal,$A27*12,Aporte*-1) -> 393819.44 | D27: =C27*Taxa_Cart -> 2362.9166
A28: 30 | B28: Quanto em 30 anos | C28: =FV(Taxa_Renda_Mensal,$A28*12,Aporte*-1) -> 1512759.4 | D28: =C28*Taxa_Cart -> 9076.5563
B30: Perfil | C30: Agressivo
B31: Valor a ser investido por mês | C31: =Aporte -> 350
B33: Tipo de Fill | C33: Percentual sugerido | D33: Valores
B34: Papel | C34: =VLOOKUP($C$30&"-"&B34,Plan2!A3:D21,4,FALSE) -> 0.5 | D34: =$C$31*C34 -> 175
B35: Tijolo | C35: =VLOOKUP($C$30&"-"&B35,Plan2!A4:D22,4,FALSE) -> 0.1 | D35: =$C$31*C35 -> 35
B36: Hibridos | C36: =VLOOKUP($C$30&"-"&B36,Plan2!A5:D23,4,FALSE) -> 0.05 | D36: =$C$31*C36 -> 17.5
B37: FOFs | C37: =VLOOKUP($C$30&"-"&B37,Plan2!A6:D24,4,FALSE) -> 0.05 | D37: =$C$31*C37 -> 17.5
B38: Desevolvimento | C38: =VLOOKUP($C$30&"-"&B38,Plan2!A7:D25,4,FALSE) -> 0.2 | D38: =$C$31*C38 -> 70
B39: Hotelarias | C39: =VLOOKUP($C$30&"-"&B39,Plan2!A8:D26,4,FALSE) -> 0.1 | D39: =$C$31*C39 -> 35
D40: =SUM(D34:D39) -> 350

Sheet Plan2
A3: Chave | B3: Perfil | C3: Tipo de Fill | D3: %
A4: =B4&"-"&C4 -> Conservador-Papel | B4: Conservador | C4: Papel | D4: 0.3
A5: =B5&"-"&C5 -> Conservador-Tijolo | B5: Conservador | C5: Tijolo | D5: 0.5
A6: =B6&"-"&C6 -> Conservador-Hibridos | B6: Conservador | C6: Hibridos | D6: 0.1
A7: =B7&"-"&C7 -> Conservador-FOFs | B7: Conservador | C7: FOFs | D7: 0.1
A8: =B8&"-"&C8 -> Conservador-Desevolvimento | B8: Conservador | C8: Desevolvimento | D8: 0
A9: =B9&"-"&C9 -> Conservador-Hotelarias | B9: Conservador | C9: Hotelarias | D9: 0
A10: =B10&"-"&C10 -> Moderado-Papel | B10: Moderado | C10: Papel | D10: 0.32
A11: =B11&"-"&C11 -> Moderado-Tijolo | B11: Moderado | C11: Tijolo | D11: 0.35
A12: =B12&"-"&C12 -> Moderado-Hibridos | B12: Moderado | C12: Hibridos | D12: 0.08
A13: =B13&"-"&C13 -> Moderado-FOFs | B13: Moderado | C13: FOFs | D13: 0.05
A14: =B14&"-"&C14 -> Moderado-Desevolvimento | B14: Moderado | C14: Desevolvimento | D14: 0.1
A15: =B15&"-"&C15 -> Moderado-Hotelarias | B15: Moderado | C15: Hotelarias | D15: 0.1
... A21: =B21&"-"&C21 -> Agressivo-Hotelarias | B21: Agressivo | C21: Hotelarias | D21: 0.1
